d_tool/__init__.py
d_tool/decr_timer.py
detool/__init__.py
detool/decr_class_exception.py
detool/decr_class_log.py
detool/decr_reids_cache.py
detool/decr_run_times.py
detool/decr_timer.py
detool-1.1.3.dist-info/LICENSE
detool-1.1.3.dist-info/METADATA
detool-1.1.3.dist-info/WHEEL
detool-1.1.3.dist-info/top_level.txt
detool-1.1.3.dist-info/RECORD
