Metadata-Version: 2.1
Name: detool
Version: 1.1.3
Summary: decorator tool collection
Home-page: UNKNOWN
Author: abo123456789
Author-email: abcdef123456chen@sohu.com
Maintainer: abo123456789
Maintainer-email: abcdef123456chen@sohu.com
License: MIT License
Keywords: detool,decorators
Platform: all
Classifier: Development Status :: 4 - Beta
Classifier: Operating System :: OS Independent
Classifier: Intended Audience :: Developers
Classifier: License :: OSI Approved :: MIT License
Classifier: Programming Language :: Python
Classifier: Programming Language :: Python :: Implementation
Classifier: Programming Language :: Python :: 3.6
Classifier: Programming Language :: Python :: 3.7
Classifier: Programming Language :: Python :: 3.8
Classifier: Programming Language :: Python :: 3.9
Classifier: Programming Language :: Python :: 3.10
Classifier: Topic :: Software Development :: Libraries
Requires-Dist: loguru (>=0.6.0)
Requires-Dist: redis (>=3.0.0)
Requires-Dist: memory-profiler (>=0.61.0)
